bee_search/__init__.py
bee_search/file_loader.py
bee_search/image_search.py
bee_search/model_embedder.py
beewant-0.0.1.dist-info/METADATA
beewant-0.0.1.dist-info/WHEEL
beewant-0.0.1.dist-info/top_level.txt
beewant-0.0.1.dist-info/RECORD
