Metadata-Version: 2.1
Name: beewant
Version: 0.0.1
Summary: Beesearch enables you to search through unstructured data using customized foundation models
Home-page: https://github.com/Beewant/beewant
Author: Beewant
Author-email: contact@beewant.fr
Requires-Dist: uvicorn
Requires-Dist: fastapi
Requires-Dist: torch
Requires-Dist: torchvision
Requires-Dist: matplotlib
Requires-Dist: transformers
Requires-Dist: pillow
Requires-Dist: typing
Requires-Dist: loguru
Requires-Dist: tqdm
Requires-Dist: googletrans (>=3.1.0a0)
Requires-Dist: python-multipart
Requires-Dist: weaviate-client
